{
  "schema_version": "2.0",
  "generated_at": "2026-07-20T05:52:15Z",
  "provider": "comtrade",
  "product_code": "TOTAL",
  "product_level": 0,
  "reporter_iso3": "COL",
  "period": "2023",
  "rows": [
    {
      "partner_iso3": "USA",
      "export_available": true,
      "import_available": true,
      "export_usd": 14112815360.42,
      "import_usd": 16181689265.44,
      "trade_usd": 30294504625.86,
      "balance_usd": -2068873905.0200005
    },
    {
      "partner_iso3": "CHN",
      "export_available": true,
      "import_available": true,
      "export_usd": 2469306485.48,
      "import_usd": 13566844921.21,
      "trade_usd": 16036151406.689999,
      "balance_usd": -11097538435.73
    },
    {
      "partner_iso3": "BRA",
      "export_available": true,
      "import_available": true,
      "export_usd": 1885420724.04,
      "import_usd": 4044885376.62,
      "trade_usd": 5930306100.66,
      "balance_usd": -2159464652.58
    },
    {
      "partner_iso3": "MEX",
      "export_available": true,
      "import_available": true,
      "export_usd": 1878578601.4,
      "import_usd": 3090354965.12,
      "trade_usd": 4968933566.52,
      "balance_usd": -1211776363.7199998
    },
    {
      "partner_iso3": "PAN",
      "export_available": true,
      "import_available": true,
      "export_usd": 4659338271.84,
      "import_usd": 28963481.67,
      "trade_usd": 4688301753.51,
      "balance_usd": 4630374790.17
    },
    {
      "partner_iso3": "IND",
      "export_available": true,
      "import_available": true,
      "export_usd": 2397798394.35,
      "import_usd": 1408537045.86,
      "trade_usd": 3806335440.21,
      "balance_usd": 989261348.49
    },
    {
      "partner_iso3": "DEU",
      "export_available": true,
      "import_available": true,
      "export_usd": 586343548.18,
      "import_usd": 2347034550.08,
      "trade_usd": 2933378098.2599998,
      "balance_usd": -1760691001.9
    },
    {
      "partner_iso3": "ECU",
      "export_available": true,
      "import_available": true,
      "export_usd": 2014886226.94,
      "import_usd": 760314482.4,
      "trade_usd": 2775200709.34,
      "balance_usd": 1254571744.54
    },
    {
      "partner_iso3": "NLD",
      "export_available": true,
      "import_available": true,
      "export_usd": 2042399893.83,
      "import_usd": 606930318.37,
      "trade_usd": 2649330212.2,
      "balance_usd": 1435469575.46
    },
    {
      "partner_iso3": "ESP",
      "export_available": true,
      "import_available": true,
      "export_usd": 1154616154.1,
      "import_usd": 1256349392.54,
      "trade_usd": 2410965546.64,
      "balance_usd": -101733238.44000006
    },
    {
      "partner_iso3": "FRA",
      "export_available": true,
      "import_available": true,
      "export_usd": 261073898.03,
      "import_usd": 2074162878.92,
      "trade_usd": 2335236776.9500003,
      "balance_usd": -1813088980.89
    },
    {
      "partner_iso3": "JPN",
      "export_available": true,
      "import_available": true,
      "export_usd": 676855199.74,
      "import_usd": 1360791503.1,
      "trade_usd": 2037646702.84,
      "balance_usd": -683936303.3599999
    },
    {
      "partner_iso3": "PER",
      "export_available": true,
      "import_available": true,
      "export_usd": 1136849305.35,
      "import_usd": 794096659.46,
      "trade_usd": 1930945964.81,
      "balance_usd": 342752645.88999987
    },
    {
      "partner_iso3": "ITA",
      "export_available": true,
      "import_available": true,
      "export_usd": 814775153.01,
      "import_usd": 1109196724.66,
      "trade_usd": 1923971877.67,
      "balance_usd": -294421571.6500001
    },
    {
      "partner_iso3": "CHL",
      "export_available": true,
      "import_available": true,
      "export_usd": 1040754918.89,
      "import_usd": 739127164.46,
      "trade_usd": 1779882083.35,
      "balance_usd": 301627754.42999995
    },
    {
      "partner_iso3": "ARG",
      "export_available": true,
      "import_available": true,
      "export_usd": 357426586.73,
      "import_usd": 1410647145.05,
      "trade_usd": 1768073731.78,
      "balance_usd": -1053220558.3199999
    },
    {
      "partner_iso3": "CAN",
      "export_available": true,
      "import_available": true,
      "export_usd": 672395801.09,
      "import_usd": 1049621188.03,
      "trade_usd": 1722016989.12,
      "balance_usd": -377225386.93999994
    },
    {
      "partner_iso3": "KOR",
      "export_available": true,
      "import_available": true,
      "export_usd": 824802033.83,
      "import_usd": 856919432.89,
      "trade_usd": 1681721466.72,
      "balance_usd": -32117399.059999943
    },
    {
      "partner_iso3": "GBR",
      "export_available": true,
      "import_available": true,
      "export_usd": 453213315.97,
      "import_usd": 704647589.3,
      "trade_usd": 1157860905.27,
      "balance_usd": -251434273.32999992
    },
    {
      "partner_iso3": "BEL",
      "export_available": true,
      "import_available": true,
      "export_usd": 539751042.94,
      "import_usd": 580204939.39,
      "trade_usd": 1119955982.33,
      "balance_usd": -40453896.44999993
    },
    {
      "partner_iso3": "POL",
      "export_available": true,
      "import_available": true,
      "export_usd": 946708760.94,
      "import_usd": 162145926.84,
      "trade_usd": 1108854687.78,
      "balance_usd": 784562834.1
    },
    {
      "partner_iso3": "TUR",
      "export_available": true,
      "import_available": true,
      "export_usd": 848363147.56,
      "import_usd": 256194266.97,
      "trade_usd": 1104557414.53,
      "balance_usd": 592168880.5899999
    },
    {
      "partner_iso3": "VNM",
      "export_available": true,
      "import_available": true,
      "export_usd": 23323232.49,
      "import_usd": 824266051.33,
      "trade_usd": 847589283.82,
      "balance_usd": -800942818.84
    },
    {
      "partner_iso3": "VEN",
      "export_available": true,
      "import_available": true,
      "export_usd": 673408355.9,
      "import_usd": 130891604.39,
      "trade_usd": 804299960.29,
      "balance_usd": 542516751.51
    },
    {
      "partner_iso3": "DOM",
      "export_available": true,
      "import_available": true,
      "export_usd": 577969011.69,
      "import_usd": 41529643.32,
      "trade_usd": 619498655.0100001,
      "balance_usd": 536439368.37000006
    },
    {
      "partner_iso3": "ISR",
      "export_available": true,
      "import_available": true,
      "export_usd": 499205361.56,
      "import_usd": 95327082.51,
      "trade_usd": 594532444.07,
      "balance_usd": 403878279.05
    },
    {
      "partner_iso3": "BOL",
      "export_available": true,
      "import_available": true,
      "export_usd": 123175069.15,
      "import_usd": 458150911.21,
      "trade_usd": 581325980.36,
      "balance_usd": -334975842.05999994
    },
    {
      "partner_iso3": "MYS",
      "export_available": true,
      "import_available": true,
      "export_usd": 320822242.14,
      "import_usd": 175485975.96,
      "trade_usd": 496308218.1,
      "balance_usd": 145336266.17999998
    },
    {
      "partner_iso3": "GTM",
      "export_available": true,
      "import_available": true,
      "export_usd": 410738035.05,
      "import_usd": 72677180.45,
      "trade_usd": 483415215.5,
      "balance_usd": 338060854.6
    },
    {
      "partner_iso3": "IRL",
      "export_available": true,
      "import_available": true,
      "export_usd": 115145650.44,
      "import_usd": 325690923.27,
      "trade_usd": 440836573.71,
      "balance_usd": -210545272.82999998
    },
    {
      "partner_iso3": "CRI",
      "export_available": true,
      "import_available": true,
      "export_usd": 345682609.83,
      "import_usd": 84538819.82,
      "trade_usd": 430221429.65,
      "balance_usd": 261143790.01
    },
    {
      "partner_iso3": "HKG",
      "export_available": true,
      "import_available": true,
      "export_usd": 364016699.35,
      "import_usd": 39512083.04,
      "trade_usd": 403528782.39000005,
      "balance_usd": 324504616.31
    },
    {
      "partner_iso3": "RUS",
      "export_available": true,
      "import_available": true,
      "export_usd": 68921838.61,
      "import_usd": 325758294.93,
      "trade_usd": 394680133.54,
      "balance_usd": -256836456.32
    },
    {
      "partner_iso3": "EGY",
      "export_available": true,
      "import_available": true,
      "export_usd": 358006780.19,
      "import_usd": 18818274.47,
      "trade_usd": 376825054.65999997,
      "balance_usd": 339188505.72
    },
    {
      "partner_iso3": "THA",
      "export_available": true,
      "import_available": true,
      "export_usd": 33095707.76,
      "import_usd": 323897140.73,
      "trade_usd": 356992848.49,
      "balance_usd": -290801432.97
    },
    {
      "partner_iso3": "ARE",
      "export_available": true,
      "import_available": true,
      "export_usd": 289365610.28,
      "import_usd": 44007045.77,
      "trade_usd": 333372656.04999995,
      "balance_usd": 245358564.50999996
    },
    {
      "partner_iso3": "SGP",
      "export_available": true,
      "import_available": true,
      "export_usd": 187893284.7,
      "import_usd": 142324241.23,
      "trade_usd": 330217525.92999995,
      "balance_usd": 45569043.47
    },
    {
      "partner_iso3": "SWE",
      "export_available": true,
      "import_available": true,
      "export_usd": 50190837.43,
      "import_usd": 278251717.85,
      "trade_usd": 328442555.28000003,
      "balance_usd": -228060880.42000002
    },
    {
      "partner_iso3": "JAM",
      "export_available": true,
      "import_available": true,
      "export_usd": 276767883.08,
      "import_usd": 699801.57,
      "trade_usd": 277467684.65,
      "balance_usd": 276068081.51
    },
    {
      "partner_iso3": "IDN",
      "export_available": true,
      "import_available": true,
      "export_usd": 8367396.95,
      "import_usd": 256994980.84,
      "trade_usd": 265362377.79,
      "balance_usd": -248627583.89000002
    },
    {
      "partner_iso3": "MAR",
      "export_available": true,
      "import_available": true,
      "export_usd": 174871469.81,
      "import_usd": 84800372.83,
      "trade_usd": 259671842.64,
      "balance_usd": 90071096.98
    },
    {
      "partner_iso3": "FIN",
      "export_available": true,
      "import_available": true,
      "export_usd": 101413706.84,
      "import_usd": 152388602.95,
      "trade_usd": 253802309.79,
      "balance_usd": -50974896.109999985
    },
    {
      "partner_iso3": "DNK",
      "export_available": true,
      "import_available": true,
      "export_usd": 27004096.66,
      "import_usd": 187916842.57,
      "trade_usd": 214920939.23,
      "balance_usd": -160912745.91
    },
    {
      "partner_iso3": "BES",
      "export_available": true,
      "import_available": false,
      "export_usd": 202075152.07,
      "import_usd": 0,
      "trade_usd": 202075152.07,
      "balance_usd": 202075152.07
    },
    {
      "partner_iso3": "NGA",
      "export_available": true,
      "import_available": true,
      "export_usd": 7968805.53,
      "import_usd": 189134615.85,
      "trade_usd": 197103421.38,
      "balance_usd": -181165810.32
    },
    {
      "partner_iso3": "AUT",
      "export_available": true,
      "import_available": true,
      "export_usd": 2057988.82,
      "import_usd": 179373368.44,
      "trade_usd": 181431357.26,
      "balance_usd": -177315379.62
    },
    {
      "partner_iso3": "SLV",
      "export_available": true,
      "import_available": true,
      "export_usd": 169917845.42,
      "import_usd": 8031110.21,
      "trade_usd": 177948955.63,
      "balance_usd": 161886735.20999998
    },
    {
      "partner_iso3": "CIV",
      "export_available": true,
      "import_available": true,
      "export_usd": 167936488.02,
      "import_usd": 5015408.79,
      "trade_usd": 172951896.81,
      "balance_usd": 162921079.23000002
    },
    {
      "partner_iso3": "HND",
      "export_available": true,
      "import_available": true,
      "export_usd": 131088493.16,
      "import_usd": 39537797.72,
      "trade_usd": 170626290.88,
      "balance_usd": 91550695.44
    },
    {
      "partner_iso3": "GUY",
      "export_available": true,
      "import_available": true,
      "export_usd": 27561585.42,
      "import_usd": 126280493.29,
      "trade_usd": 153842078.71,
      "balance_usd": -98718907.87
    },
    {
      "partner_iso3": "AUS",
      "export_available": true,
      "import_available": true,
      "export_usd": 98259072.18,
      "import_usd": 50887327.3,
      "trade_usd": 149146399.48000002,
      "balance_usd": 47371744.88000001
    },
    {
      "partner_iso3": "SAU",
      "export_available": true,
      "import_available": true,
      "export_usd": 96820228.25,
      "import_usd": 51765250.69,
      "trade_usd": 148585478.94,
      "balance_usd": 45054977.56
    },
    {
      "partner_iso3": "TTO",
      "export_available": true,
      "import_available": true,
      "export_usd": 40965174.03,
      "import_usd": 98147312.14,
      "trade_usd": 139112486.17000002,
      "balance_usd": -57182138.11
    },
    {
      "partner_iso3": "URY",
      "export_available": true,
      "import_available": true,
      "export_usd": 28242998.6,
      "import_usd": 103264050.04,
      "trade_usd": 131507048.64000002,
      "balance_usd": -75021051.44
    },
    {
      "partner_iso3": "CZE",
      "export_available": true,
      "import_available": true,
      "export_usd": 7207780.77,
      "import_usd": 121676710.7,
      "trade_usd": 128884491.47,
      "balance_usd": -114468929.93
    },
    {
      "partner_iso3": "BHS",
      "export_available": true,
      "import_available": true,
      "export_usd": 112003465.34,
      "import_usd": 16245796.82,
      "trade_usd": 128249262.16,
      "balance_usd": 95757668.52000001
    },
    {
      "partner_iso3": "DZA",
      "export_available": true,
      "import_available": true,
      "export_usd": 1347594.8,
      "import_usd": 124852016.71,
      "trade_usd": 126199611.50999999,
      "balance_usd": -123504421.91
    },
    {
      "partner_iso3": "NOR",
      "export_available": true,
      "import_available": true,
      "export_usd": 75359099.93,
      "import_usd": 44459161.01,
      "trade_usd": 119818260.94,
      "balance_usd": 30899938.92000001
    },
    {
      "partner_iso3": "HUN",
      "export_available": true,
      "import_available": true,
      "export_usd": 2080499.12,
      "import_usd": 115596480.07,
      "trade_usd": 117676979.19,
      "balance_usd": -113515980.94999999
    },
    {
      "partner_iso3": "ZAF",
      "export_available": true,
      "import_available": true,
      "export_usd": 76970301.91,
      "import_usd": 39340005.36,
      "trade_usd": 116310307.27,
      "balance_usd": 37630296.55
    },
    {
      "partner_iso3": "ROU",
      "export_available": true,
      "import_available": true,
      "export_usd": 14783723.16,
      "import_usd": 98865176.04,
      "trade_usd": 113648899.2,
      "balance_usd": -84081452.88000001
    },
    {
      "partner_iso3": "PRT",
      "export_available": true,
      "import_available": true,
      "export_usd": 24109770.94,
      "import_usd": 86319670.16,
      "trade_usd": 110429441.1,
      "balance_usd": -62209899.22
    },
    {
      "partner_iso3": "BGD",
      "export_available": true,
      "import_available": true,
      "export_usd": 2146472.03,
      "import_usd": 104245171.97,
      "trade_usd": 106391644,
      "balance_usd": -102098699.94
    },
    {
      "partner_iso3": "SVN",
      "export_available": true,
      "import_available": true,
      "export_usd": 61896496.8,
      "import_usd": 38586883.89,
      "trade_usd": 100483380.69,
      "balance_usd": 23309612.909999996
    },
    {
      "partner_iso3": "PRY",
      "export_available": true,
      "import_available": true,
      "export_usd": 27951477.94,
      "import_usd": 55167434.03,
      "trade_usd": 83118911.97,
      "balance_usd": -27215956.09
    },
    {
      "partner_iso3": "SVK",
      "export_available": true,
      "import_available": true,
      "export_usd": 2011334.96,
      "import_usd": 69991286.56,
      "trade_usd": 72002621.52,
      "balance_usd": -67979951.60000001
    },
    {
      "partner_iso3": "HTI",
      "export_available": true,
      "import_available": true,
      "export_usd": 65564454.93,
      "import_usd": 493211.14,
      "trade_usd": 66057666.07,
      "balance_usd": 65071243.79
    },
    {
      "partner_iso3": "NIC",
      "export_available": true,
      "import_available": true,
      "export_usd": 45893260.98,
      "import_usd": 18017173.26,
      "trade_usd": 63910434.239999995,
      "balance_usd": 27876087.719999995
    },
    {
      "partner_iso3": "PHL",
      "export_available": true,
      "import_available": true,
      "export_usd": 11610928.06,
      "import_usd": 49143671.89,
      "trade_usd": 60754599.95,
      "balance_usd": -37532743.83
    },
    {
      "partner_iso3": "CUW",
      "export_available": true,
      "import_available": true,
      "export_usd": 60568838.74,
      "import_usd": 163.47,
      "trade_usd": 60569002.21,
      "balance_usd": 60568675.27
    },
    {
      "partner_iso3": "BHR",
      "export_available": true,
      "import_available": true,
      "export_usd": 1442609.6,
      "import_usd": 58648086.53,
      "trade_usd": 60090696.13,
      "balance_usd": -57205476.93
    },
    {
      "partner_iso3": "IRQ",
      "export_available": true,
      "import_available": true,
      "export_usd": 58066320,
      "import_usd": 186883.99,
      "trade_usd": 58253203.99,
      "balance_usd": 57879436.01
    },
    {
      "partner_iso3": "CUB",
      "export_available": true,
      "import_available": true,
      "export_usd": 52905824.93,
      "import_usd": 2110505.75,
      "trade_usd": 55016330.68,
      "balance_usd": 50795319.18
    },
    {
      "partner_iso3": "PAK",
      "export_available": true,
      "import_available": true,
      "export_usd": 1250855.88,
      "import_usd": 46295589.84,
      "trade_usd": 47546445.720000006,
      "balance_usd": -45044733.96
    },
    {
      "partner_iso3": "KHM",
      "export_available": true,
      "import_available": true,
      "export_usd": 119760.17,
      "import_usd": 45823871.98,
      "trade_usd": 45943632.15,
      "balance_usd": -45704111.809999995
    },
    {
      "partner_iso3": "GRC",
      "export_available": true,
      "import_available": true,
      "export_usd": 20603645.78,
      "import_usd": 22494913.87,
      "trade_usd": 43098559.650000006,
      "balance_usd": -1891268.0899999999
    },
    {
      "partner_iso3": "BGR",
      "export_available": true,
      "import_available": true,
      "export_usd": 25646887.12,
      "import_usd": 17264443.64,
      "trade_usd": 42911330.760000005,
      "balance_usd": 8382443.48
    },
    {
      "partner_iso3": "LTU",
      "export_available": true,
      "import_available": true,
      "export_usd": 1850092.28,
      "import_usd": 39516146.81,
      "trade_usd": 41366239.09,
      "balance_usd": -37666054.53
    },
    {
      "partner_iso3": "ABW",
      "export_available": true,
      "import_available": true,
      "export_usd": 39126156.72,
      "import_usd": 6672.52,
      "trade_usd": 39132829.24,
      "balance_usd": 39119484.199999996
    },
    {
      "partner_iso3": "NZL",
      "export_available": true,
      "import_available": true,
      "export_usd": 16111427.77,
      "import_usd": 21394737.28,
      "trade_usd": 37506165.05,
      "balance_usd": -5283309.510000002
    },
    {
      "partner_iso3": "UKR",
      "export_available": true,
      "import_available": true,
      "export_usd": 2158390.06,
      "import_usd": 35160258.82,
      "trade_usd": 37318648.88,
      "balance_usd": -33001868.76
    },
    {
      "partner_iso3": "HRV",
      "export_available": true,
      "import_available": true,
      "export_usd": 16389345.84,
      "import_usd": 19022132.17,
      "trade_usd": 35411478.010000005,
      "balance_usd": -2632786.330000002
    },
    {
      "partner_iso3": "BRN",
      "export_available": true,
      "import_available": true,
      "export_usd": 25334816.83,
      "import_usd": 8296566.95,
      "trade_usd": 33631383.78,
      "balance_usd": 17038249.88
    },
    {
      "partner_iso3": "GAB",
      "export_available": true,
      "import_available": true,
      "export_usd": 28881573.71,
      "import_usd": 3588.5,
      "trade_usd": 28885162.21,
      "balance_usd": 28877985.21
    },
    {
      "partner_iso3": "JOR",
      "export_available": true,
      "import_available": true,
      "export_usd": 26135511.6,
      "import_usd": 2052038.31,
      "trade_usd": 28187549.91,
      "balance_usd": 24083473.290000003
    },
    {
      "partner_iso3": "LVA",
      "export_available": true,
      "import_available": true,
      "export_usd": 13612546.45,
      "import_usd": 7160650.21,
      "trade_usd": 20773196.66,
      "balance_usd": 6451896.239999999
    },
    {
      "partner_iso3": "KAZ",
      "export_available": true,
      "import_available": true,
      "export_usd": 16463146.84,
      "import_usd": 2374073.78,
      "trade_usd": 18837220.62,
      "balance_usd": 14089073.06
    },
    {
      "partner_iso3": "LKA",
      "export_available": true,
      "import_available": true,
      "export_usd": 740103.39,
      "import_usd": 17654031.9,
      "trade_usd": 18394135.29,
      "balance_usd": -16913928.509999998
    },
    {
      "partner_iso3": "LBN",
      "export_available": true,
      "import_available": true,
      "export_usd": 17313049.47,
      "import_usd": 441556.68,
      "trade_usd": 17754606.15,
      "balance_usd": 16871492.79
    },
    {
      "partner_iso3": "MMR",
      "export_available": false,
      "import_available": true,
      "export_usd": 0,
      "import_usd": 14482687.13,
      "trade_usd": 14482687.13,
      "balance_usd": -14482687.13
    },
    {
      "partner_iso3": "SUR",
      "export_available": true,
      "import_available": true,
      "export_usd": 12560810.85,
      "import_usd": 1849307.84,
      "trade_usd": 14410118.69,
      "balance_usd": 10711503.01
    },
    {
      "partner_iso3": "SEN",
      "export_available": true,
      "import_available": true,
      "export_usd": 1470800.91,
      "import_usd": 12158187.68,
      "trade_usd": 13628988.59,
      "balance_usd": -10687386.77
    },
    {
      "partner_iso3": "ALB",
      "export_available": true,
      "import_available": true,
      "export_usd": 12298966.59,
      "import_usd": 201866.84,
      "trade_usd": 12500833.43,
      "balance_usd": 12097099.75
    },
    {
      "partner_iso3": "OMN",
      "export_available": true,
      "import_available": true,
      "export_usd": 2015733.69,
      "import_usd": 8990243.91,
      "trade_usd": 11005977.6,
      "balance_usd": -6974510.220000001
    },
    {
      "partner_iso3": "BRB",
      "export_available": true,
      "import_available": true,
      "export_usd": 10036971.54,
      "import_usd": 867986.63,
      "trade_usd": 10904958.17,
      "balance_usd": 9168984.909999998
    },
    {
      "partner_iso3": "CYM",
      "export_available": true,
      "import_available": false,
      "export_usd": 9190462.33,
      "import_usd": 0,
      "trade_usd": 9190462.33,
      "balance_usd": 9190462.33
    },
    {
      "partner_iso3": "NCL",
      "export_available": true,
      "import_available": true,
      "export_usd": 8846964.44,
      "import_usd": 10004.04,
      "trade_usd": 8856968.479999999,
      "balance_usd": 8836960.4
    },
    {
      "partner_iso3": "LUX",
      "export_available": true,
      "import_available": true,
      "export_usd": 760392.53,
      "import_usd": 7373931.55,
      "trade_usd": 8134324.08,
      "balance_usd": -6613539.02
    },
    {
      "partner_iso3": "BLZ",
      "export_available": true,
      "import_available": true,
      "export_usd": 7478888.71,
      "import_usd": 25141.55,
      "trade_usd": 7504030.26,
      "balance_usd": 7453747.16
    },
    {
      "partner_iso3": "TUN",
      "export_available": true,
      "import_available": true,
      "export_usd": 124952.86,
      "import_usd": 6951523.04,
      "trade_usd": 7076475.9,
      "balance_usd": -6826570.18
    },
    {
      "partner_iso3": "LBY",
      "export_available": true,
      "import_available": true,
      "export_usd": 5989963.67,
      "import_usd": 13856.33,
      "trade_usd": 6003820,
      "balance_usd": 5976107.34
    },
    {
      "partner_iso3": "BIH",
      "export_available": true,
      "import_available": true,
      "export_usd": 156340.41,
      "import_usd": 5568909.14,
      "trade_usd": 5725249.55,
      "balance_usd": -5412568.7299999995
    },
    {
      "partner_iso3": "EST",
      "export_available": true,
      "import_available": true,
      "export_usd": 1568492.62,
      "import_usd": 3340024.75,
      "trade_usd": 4908517.37,
      "balance_usd": -1771532.13
    },
    {
      "partner_iso3": "MOZ",
      "export_available": true,
      "import_available": true,
      "export_usd": 4723866.11,
      "import_usd": 19774.22,
      "trade_usd": 4743640.33,
      "balance_usd": 4704091.890000001
    },
    {
      "partner_iso3": "KWT",
      "export_available": true,
      "import_available": true,
      "export_usd": 4477688.79,
      "import_usd": 46804.48,
      "trade_usd": 4524493.2700000005,
      "balance_usd": 4430884.31
    },
    {
      "partner_iso3": "MLT",
      "export_available": true,
      "import_available": true,
      "export_usd": 232112.47,
      "import_usd": 4251278.12,
      "trade_usd": 4483390.59,
      "balance_usd": -4019165.65
    },
    {
      "partner_iso3": "MUS",
      "export_available": true,
      "import_available": true,
      "export_usd": 3970837.71,
      "import_usd": 459260.84,
      "trade_usd": 4430098.55,
      "balance_usd": 3511576.87
    },
    {
      "partner_iso3": "GEO",
      "export_available": true,
      "import_available": true,
      "export_usd": 1103470.85,
      "import_usd": 2996079.46,
      "trade_usd": 4099550.31,
      "balance_usd": -1892608.6099999999
    },
    {
      "partner_iso3": "QAT",
      "export_available": true,
      "import_available": true,
      "export_usd": 2882607.29,
      "import_usd": 933212.14,
      "trade_usd": 3815819.43,
      "balance_usd": 1949395.15
    },
    {
      "partner_iso3": "GHA",
      "export_available": true,
      "import_available": true,
      "export_usd": 2666198.61,
      "import_usd": 884085.91,
      "trade_usd": 3550284.52,
      "balance_usd": 1782112.6999999997
    },
    {
      "partner_iso3": "COG",
      "export_available": true,
      "import_available": true,
      "export_usd": 3401247.36,
      "import_usd": 398.39,
      "trade_usd": 3401645.75,
      "balance_usd": 3400848.9699999997
    },
    {
      "partner_iso3": "ATG",
      "export_available": true,
      "import_available": true,
      "export_usd": 3237649.1,
      "import_usd": 2361.57,
      "trade_usd": 3240010.67,
      "balance_usd": 3235287.5300000003
    },
    {
      "partner_iso3": "BLR",
      "export_available": true,
      "import_available": true,
      "export_usd": 2417608.57,
      "import_usd": 299212,
      "trade_usd": 2716820.57,
      "balance_usd": 2118396.57
    },
    {
      "partner_iso3": "KEN",
      "export_available": true,
      "import_available": true,
      "export_usd": 1261605.07,
      "import_usd": 1424202.7,
      "trade_usd": 2685807.77,
      "balance_usd": -162597.6299999999
    },
    {
      "partner_iso3": "MDA",
      "export_available": true,
      "import_available": true,
      "export_usd": 559646.4,
      "import_usd": 2121353.64,
      "trade_usd": 2681000.04,
      "balance_usd": -1561707.2400000002
    },
    {
      "partner_iso3": "AGO",
      "export_available": true,
      "import_available": true,
      "export_usd": 2605855.15,
      "import_usd": 2884.19,
      "trade_usd": 2608739.34,
      "balance_usd": 2602970.96
    },
    {
      "partner_iso3": "ISL",
      "export_available": true,
      "import_available": true,
      "export_usd": 347664.16,
      "import_usd": 2256911.58,
      "trade_usd": 2604575.74,
      "balance_usd": -1909247.4200000002
    },
    {
      "partner_iso3": "TCA",
      "export_available": true,
      "import_available": false,
      "export_usd": 2485645.5,
      "import_usd": 0,
      "trade_usd": 2485645.5,
      "balance_usd": 2485645.5
    },
    {
      "partner_iso3": "LCA",
      "export_available": true,
      "import_available": true,
      "export_usd": 2371966.73,
      "import_usd": 5818.46,
      "trade_usd": 2377785.19,
      "balance_usd": 2366148.27
    },
    {
      "partner_iso3": "LAO",
      "export_available": true,
      "import_available": true,
      "export_usd": 5272,
      "import_usd": 2357817.12,
      "trade_usd": 2363089.12,
      "balance_usd": -2352545.12
    },
    {
      "partner_iso3": "GRD",
      "export_available": true,
      "import_available": true,
      "export_usd": 2319449.38,
      "import_usd": 31336.95,
      "trade_usd": 2350786.33,
      "balance_usd": 2288112.4299999997
    },
    {
      "partner_iso3": "CMR",
      "export_available": true,
      "import_available": true,
      "export_usd": 2284476.81,
      "import_usd": 27969.35,
      "trade_usd": 2312446.16,
      "balance_usd": 2256507.46
    },
    {
      "partner_iso3": "DMA",
      "export_available": true,
      "import_available": true,
      "export_usd": 1923764.59,
      "import_usd": 19186.46,
      "trade_usd": 1942951.05,
      "balance_usd": 1904578.1300000001
    },
    {
      "partner_iso3": "VCT",
      "export_available": true,
      "import_available": true,
      "export_usd": 1654361.46,
      "import_usd": 1784.7,
      "trade_usd": 1656146.16,
      "balance_usd": 1652576.76
    },
    {
      "partner_iso3": "GIN",
      "export_available": true,
      "import_available": true,
      "export_usd": 1493836.72,
      "import_usd": 9678.28,
      "trade_usd": 1503515,
      "balance_usd": 1484158.44
    },
    {
      "partner_iso3": "DJI",
      "export_available": true,
      "import_available": true,
      "export_usd": 1437876,
      "import_usd": 48.47,
      "trade_usd": 1437924.47,
      "balance_usd": 1437827.53
    },
    {
      "partner_iso3": "MDG",
      "export_available": true,
      "import_available": true,
      "export_usd": 435513.22,
      "import_usd": 867350.18,
      "trade_usd": 1302863.4,
      "balance_usd": -431836.9600000001
    },
    {
      "partner_iso3": "TZA",
      "export_available": true,
      "import_available": true,
      "export_usd": 640606.98,
      "import_usd": 444225.49,
      "trade_usd": 1084832.47,
      "balance_usd": 196381.49
    },
    {
      "partner_iso3": "KNA",
      "export_available": true,
      "import_available": true,
      "export_usd": 964497.88,
      "import_usd": 100039.71,
      "trade_usd": 1064537.59,
      "balance_usd": 864458.17
    },
    {
      "partner_iso3": "CYP",
      "export_available": true,
      "import_available": true,
      "export_usd": 395688.04,
      "import_usd": 566673.05,
      "trade_usd": 962361.0900000001,
      "balance_usd": -170985.01000000007
    },
    {
      "partner_iso3": "LBR",
      "export_available": true,
      "import_available": true,
      "export_usd": 890567.17,
      "import_usd": 14413.95,
      "trade_usd": 904981.12,
      "balance_usd": 876153.2200000001
    },
    {
      "partner_iso3": "TGO",
      "export_available": true,
      "import_available": true,
      "export_usd": 861555.11,
      "import_usd": 23343.2,
      "trade_usd": 884898.3099999999,
      "balance_usd": 838211.91
    },
    {
      "partner_iso3": "MAC",
      "export_available": true,
      "import_available": true,
      "export_usd": 687151.95,
      "import_usd": 165575.27,
      "trade_usd": 852727.22,
      "balance_usd": 521576.67999999993
    },
    {
      "partner_iso3": "SLE",
      "export_available": true,
      "import_available": true,
      "export_usd": 743407.77,
      "import_usd": 12103.51,
      "trade_usd": 755511.28,
      "balance_usd": 731304.26
    },
    {
      "partner_iso3": "VGB",
      "export_available": true,
      "import_available": true,
      "export_usd": 581204.43,
      "import_usd": 172767.87,
      "trade_usd": 753972.3,
      "balance_usd": 408436.56000000006
    },
    {
      "partner_iso3": "CPV",
      "export_available": true,
      "import_available": true,
      "export_usd": 706116.82,
      "import_usd": 7548.26,
      "trade_usd": 713665.08,
      "balance_usd": 698568.5599999999
    },
    {
      "partner_iso3": "ARM",
      "export_available": true,
      "import_available": true,
      "export_usd": 669744.31,
      "import_usd": 35144.27,
      "trade_usd": 704888.5800000001,
      "balance_usd": 634600.04
    },
    {
      "partner_iso3": "SYR",
      "export_available": true,
      "import_available": true,
      "export_usd": 307997,
      "import_usd": 343795.35,
      "trade_usd": 651792.35,
      "balance_usd": -35798.34999999998
    },
    {
      "partner_iso3": "IRN",
      "export_available": false,
      "import_available": true,
      "export_usd": 0,
      "import_usd": 537305.55,
      "trade_usd": 537305.55,
      "balance_usd": -537305.55
    },
    {
      "partner_iso3": "MRT",
      "export_available": true,
      "import_available": true,
      "export_usd": 489023.84,
      "import_usd": 27038.36,
      "trade_usd": 516062.2,
      "balance_usd": 461985.48000000004
    },
    {
      "partner_iso3": "MNE",
      "export_available": true,
      "import_available": false,
      "export_usd": 499508.76,
      "import_usd": 0,
      "trade_usd": 499508.76,
      "balance_usd": 499508.76
    },
    {
      "partner_iso3": "PSE",
      "export_available": true,
      "import_available": true,
      "export_usd": 361754.96,
      "import_usd": 99042.03,
      "trade_usd": 460796.99,
      "balance_usd": 262712.93000000005
    },
    {
      "partner_iso3": "MWI",
      "export_available": true,
      "import_available": true,
      "export_usd": 454569.46,
      "import_usd": 922.44,
      "trade_usd": 455491.9,
      "balance_usd": 453647.02
    },
    {
      "partner_iso3": "KGZ",
      "export_available": true,
      "import_available": true,
      "export_usd": 352573.8,
      "import_usd": 87999.11,
      "trade_usd": 440572.91,
      "balance_usd": 264574.69
    },
    {
      "partner_iso3": "MLI",
      "export_available": true,
      "import_available": true,
      "export_usd": 434831.02,
      "import_usd": 3791.81,
      "trade_usd": 438622.83,
      "balance_usd": 431039.21
    },
    {
      "partner_iso3": "UZB",
      "export_available": true,
      "import_available": true,
      "export_usd": 145450.19,
      "import_usd": 287421.86,
      "trade_usd": 432872.05,
      "balance_usd": -141971.66999999998
    },
    {
      "partner_iso3": "PRK",
      "export_available": false,
      "import_available": true,
      "export_usd": 0,
      "import_usd": 431467.68,
      "trade_usd": 431467.68,
      "balance_usd": -431467.68
    },
    {
      "partner_iso3": "MKD",
      "export_available": true,
      "import_available": true,
      "export_usd": 287157.26,
      "import_usd": 126736.57,
      "trade_usd": 413893.83,
      "balance_usd": 160420.69
    },
    {
      "partner_iso3": "SRB",
      "export_available": true,
      "import_available": true,
      "export_usd": 57512,
      "import_usd": 353253.37,
      "trade_usd": 410765.37,
      "balance_usd": -295741.37
    },
    {
      "partner_iso3": "UGA",
      "export_available": true,
      "import_available": true,
      "export_usd": 294973.8,
      "import_usd": 109062.37,
      "trade_usd": 404036.17,
      "balance_usd": 185911.43
    },
    {
      "partner_iso3": "COD",
      "export_available": true,
      "import_available": false,
      "export_usd": 378455.57,
      "import_usd": 0,
      "trade_usd": 378455.57,
      "balance_usd": 378455.57
    },
    {
      "partner_iso3": "AZE",
      "export_available": true,
      "import_available": true,
      "export_usd": 216792.01,
      "import_usd": 99688.12,
      "trade_usd": 316480.13,
      "balance_usd": 117103.89000000001
    },
    {
      "partner_iso3": "GUM",
      "export_available": true,
      "import_available": true,
      "export_usd": 310484.15,
      "import_usd": 28.34,
      "trade_usd": 310512.49000000005,
      "balance_usd": 310455.81
    },
    {
      "partner_iso3": "ETH",
      "export_available": true,
      "import_available": true,
      "export_usd": 295227.24,
      "import_usd": 14206.24,
      "trade_usd": 309433.48,
      "balance_usd": 281021
    },
    {
      "partner_iso3": "TCD",
      "export_available": true,
      "import_available": true,
      "export_usd": 294380.47,
      "import_usd": 9345.88,
      "trade_usd": 303726.35,
      "balance_usd": 285034.58999999997
    },
    {
      "partner_iso3": "YEM",
      "export_available": true,
      "import_available": false,
      "export_usd": 257140,
      "import_usd": 0,
      "trade_usd": 257140,
      "balance_usd": 257140
    },
    {
      "partner_iso3": "AIA",
      "export_available": true,
      "import_available": true,
      "export_usd": 28903.23,
      "import_usd": 224230.7,
      "trade_usd": 253133.93000000002,
      "balance_usd": -195327.47
    },
    {
      "partner_iso3": "SDN",
      "export_available": true,
      "import_available": true,
      "export_usd": 56100,
      "import_usd": 192082.26,
      "trade_usd": 248182.26,
      "balance_usd": -135982.26
    },
    {
      "partner_iso3": "TKL",
      "export_available": false,
      "import_available": true,
      "export_usd": 0,
      "import_usd": 217335.02,
      "trade_usd": 217335.02,
      "balance_usd": -217335.02
    },
    {
      "partner_iso3": "PNG",
      "export_available": true,
      "import_available": true,
      "export_usd": 151275,
      "import_usd": 61935.89,
      "trade_usd": 213210.89,
      "balance_usd": 89339.11
    },
    {
      "partner_iso3": "BMU",
      "export_available": true,
      "import_available": true,
      "export_usd": 210596.36,
      "import_usd": 268.2,
      "trade_usd": 210864.56,
      "balance_usd": 210328.15999999997
    },
    {
      "partner_iso3": "FJI",
      "export_available": true,
      "import_available": true,
      "export_usd": 182974.84,
      "import_usd": 13024.5,
      "trade_usd": 195999.34,
      "balance_usd": 169950.34
    },
    {
      "partner_iso3": "GNQ",
      "export_available": true,
      "import_available": false,
      "export_usd": 173563.37,
      "import_usd": 0,
      "trade_usd": 173563.37,
      "balance_usd": 173563.37
    },
    {
      "partner_iso3": "PCN",
      "export_available": false,
      "import_available": true,
      "export_usd": 0,
      "import_usd": 133936.85,
      "trade_usd": 133936.85,
      "balance_usd": -133936.85
    },
    {
      "partner_iso3": "GNB",
      "export_available": true,
      "import_available": false,
      "export_usd": 107877.96,
      "import_usd": 0,
      "trade_usd": 107877.96,
      "balance_usd": 107877.96
    },
    {
      "partner_iso3": "WSM",
      "export_available": false,
      "import_available": true,
      "export_usd": 0,
      "import_usd": 88021.18,
      "trade_usd": 88021.18,
      "balance_usd": -88021.18
    },
    {
      "partner_iso3": "TJK",
      "export_available": true,
      "import_available": false,
      "export_usd": 83422.51,
      "import_usd": 0,
      "trade_usd": 83422.51,
      "balance_usd": 83422.51
    },
    {
      "partner_iso3": "BEN",
      "export_available": true,
      "import_available": true,
      "export_usd": 79142.37,
      "import_usd": 2271.89,
      "trade_usd": 81414.26,
      "balance_usd": 76870.48
    },
    {
      "partner_iso3": "NRU",
      "export_available": false,
      "import_available": true,
      "export_usd": 0,
      "import_usd": 71978.04,
      "trade_usd": 71978.04,
      "balance_usd": -71978.04
    },
    {
      "partner_iso3": "TON",
      "export_available": true,
      "import_available": true,
      "export_usd": 61440,
      "import_usd": 4121.04,
      "trade_usd": 65561.04,
      "balance_usd": 57318.96
    },
    {
      "partner_iso3": "ASM",
      "export_available": true,
      "import_available": true,
      "export_usd": 61440,
      "import_usd": 428.73,
      "trade_usd": 61868.73,
      "balance_usd": 61011.27
    },
    {
      "partner_iso3": "SWZ",
      "export_available": false,
      "import_available": true,
      "export_usd": 0,
      "import_usd": 57088.86,
      "trade_usd": 57088.86,
      "balance_usd": -57088.86
    },
    {
      "partner_iso3": "COM",
      "export_available": true,
      "import_available": true,
      "export_usd": 46490.65,
      "import_usd": 3830.9,
      "trade_usd": 50321.55,
      "balance_usd": 42659.75
    },
    {
      "partner_iso3": "SYC",
      "export_available": false,
      "import_available": true,
      "export_usd": 0,
      "import_usd": 47130.85,
      "trade_usd": 47130.85,
      "balance_usd": -47130.85
    },
    {
      "partner_iso3": "BFA",
      "export_available": true,
      "import_available": true,
      "export_usd": 35240.62,
      "import_usd": 2027.47,
      "trade_usd": 37268.090000000004,
      "balance_usd": 33213.15
    },
    {
      "partner_iso3": "BTN",
      "export_available": false,
      "import_available": true,
      "export_usd": 0,
      "import_usd": 36342.18,
      "trade_usd": 36342.18,
      "balance_usd": -36342.18
    },
    {
      "partner_iso3": "ZWE",
      "export_available": true,
      "import_available": true,
      "export_usd": 9472.8,
      "import_usd": 23977.11,
      "trade_usd": 33449.91,
      "balance_usd": -14504.310000000001
    },
    {
      "partner_iso3": "CCK",
      "export_available": false,
      "import_available": true,
      "export_usd": 0,
      "import_usd": 32994.87,
      "trade_usd": 32994.87,
      "balance_usd": -32994.87
    },
    {
      "partner_iso3": "MDV",
      "export_available": true,
      "import_available": true,
      "export_usd": 28785.14,
      "import_usd": 588.24,
      "trade_usd": 29373.38,
      "balance_usd": 28196.899999999998
    },
    {
      "partner_iso3": "ERI",
      "export_available": false,
      "import_available": true,
      "export_usd": 0,
      "import_usd": 24690.36,
      "trade_usd": 24690.36,
      "balance_usd": -24690.36
    },
    {
      "partner_iso3": "TKM",
      "export_available": false,
      "import_available": true,
      "export_usd": 0,
      "import_usd": 21093.87,
      "trade_usd": 21093.87,
      "balance_usd": -21093.87
    },
    {
      "partner_iso3": "SLB",
      "export_available": false,
      "import_available": true,
      "export_usd": 0,
      "import_usd": 20976.5,
      "trade_usd": 20976.5,
      "balance_usd": -20976.5
    },
    {
      "partner_iso3": "SMR",
      "export_available": true,
      "import_available": true,
      "export_usd": 10367.54,
      "import_usd": 10292.92,
      "trade_usd": 20660.46,
      "balance_usd": 74.6200000000008
    },
    {
      "partner_iso3": "MSR",
      "export_available": true,
      "import_available": false,
      "export_usd": 20055.73,
      "import_usd": 0,
      "trade_usd": 20055.73,
      "balance_usd": 20055.73
    },
    {
      "partner_iso3": "LSO",
      "export_available": false,
      "import_available": true,
      "export_usd": 0,
      "import_usd": 19457.2,
      "trade_usd": 19457.2,
      "balance_usd": -19457.2
    },
    {
      "partner_iso3": "AND",
      "export_available": false,
      "import_available": true,
      "export_usd": 0,
      "import_usd": 19141.15,
      "trade_usd": 19141.15,
      "balance_usd": -19141.15
    },
    {
      "partner_iso3": "NAM",
      "export_available": false,
      "import_available": true,
      "export_usd": 0,
      "import_usd": 16539.67,
      "trade_usd": 16539.67,
      "balance_usd": -16539.67
    },
    {
      "partner_iso3": "STP",
      "export_available": false,
      "import_available": true,
      "export_usd": 0,
      "import_usd": 10849.36,
      "trade_usd": 10849.36,
      "balance_usd": -10849.36
    },
    {
      "partner_iso3": "GMB",
      "export_available": true,
      "import_available": true,
      "export_usd": 5500,
      "import_usd": 3706.7,
      "trade_usd": 9206.7,
      "balance_usd": 1793.3000000000002
    },
    {
      "partner_iso3": "CAF",
      "export_available": false,
      "import_available": true,
      "export_usd": 0,
      "import_usd": 8690.66,
      "trade_usd": 8690.66,
      "balance_usd": -8690.66
    },
    {
      "partner_iso3": "BWA",
      "export_available": true,
      "import_available": true,
      "export_usd": 6100,
      "import_usd": 811.66,
      "trade_usd": 6911.66,
      "balance_usd": 5288.34
    },
    {
      "partner_iso3": "AFG",
      "export_available": false,
      "import_available": true,
      "export_usd": 0,
      "import_usd": 6616.64,
      "trade_usd": 6616.64,
      "balance_usd": -6616.64
    },
    {
      "partner_iso3": "NER",
      "export_available": false,
      "import_available": true,
      "export_usd": 0,
      "import_usd": 6572.55,
      "trade_usd": 6572.55,
      "balance_usd": -6572.55
    },
    {
      "partner_iso3": "RWA",
      "export_available": true,
      "import_available": false,
      "export_usd": 6085,
      "import_usd": 0,
      "trade_usd": 6085,
      "balance_usd": 6085
    },
    {
      "partner_iso3": "NIU",
      "export_available": false,
      "import_available": true,
      "export_usd": 0,
      "import_usd": 5682.54,
      "trade_usd": 5682.54,
      "balance_usd": -5682.54
    },
    {
      "partner_iso3": "SOM",
      "export_available": false,
      "import_available": true,
      "export_usd": 0,
      "import_usd": 5558.45,
      "trade_usd": 5558.45,
      "balance_usd": -5558.45
    },
    {
      "partner_iso3": "NPL",
      "export_available": false,
      "import_available": true,
      "export_usd": 0,
      "import_usd": 1794.33,
      "trade_usd": 1794.33,
      "balance_usd": -1794.33
    },
    {
      "partner_iso3": "FRO",
      "export_available": false,
      "import_available": true,
      "export_usd": 0,
      "import_usd": 1384.73,
      "trade_usd": 1384.73,
      "balance_usd": -1384.73
    },
    {
      "partner_iso3": "PYF",
      "export_available": true,
      "import_available": false,
      "export_usd": 1216.83,
      "import_usd": 0,
      "trade_usd": 1216.83,
      "balance_usd": 1216.83
    },
    {
      "partner_iso3": "GIB",
      "export_available": false,
      "import_available": true,
      "export_usd": 0,
      "import_usd": 1130.6,
      "trade_usd": 1130.6,
      "balance_usd": -1130.6
    },
    {
      "partner_iso3": "BDI",
      "export_available": false,
      "import_available": true,
      "export_usd": 0,
      "import_usd": 1024.59,
      "trade_usd": 1024.59,
      "balance_usd": -1024.59
    },
    {
      "partner_iso3": "SHN",
      "export_available": false,
      "import_available": true,
      "export_usd": 0,
      "import_usd": 1015,
      "trade_usd": 1015,
      "balance_usd": -1015
    },
    {
      "partner_iso3": "GRL",
      "export_available": false,
      "import_available": true,
      "export_usd": 0,
      "import_usd": 551.44,
      "trade_usd": 551.44,
      "balance_usd": -551.44
    },
    {
      "partner_iso3": "ZMB",
      "export_available": true,
      "import_available": false,
      "export_usd": 400,
      "import_usd": 0,
      "trade_usd": 400,
      "balance_usd": 400
    },
    {
      "partner_iso3": "CXR",
      "export_available": false,
      "import_available": true,
      "export_usd": 0,
      "import_usd": 241.91,
      "trade_usd": 241.91,
      "balance_usd": -241.91
    },
    {
      "partner_iso3": "TLS",
      "export_available": false,
      "import_available": true,
      "export_usd": 0,
      "import_usd": 58.03,
      "trade_usd": 58.03,
      "balance_usd": -58.03
    },
    {
      "partner_iso3": "MNP",
      "export_available": false,
      "import_available": true,
      "export_usd": 0,
      "import_usd": 6.36,
      "trade_usd": 6.36,
      "balance_usd": -6.36
    }
  ]
}
